[
    
    {
        "id": "cafe-1",
        "titulo": "Capuccino",
        "imagen": "./img/products/capuccino.jpg",
        "detalles": "Preparado con café expreso y leche montada con vapor para darle cremosidad. Un capuchino se compone de 125 ml de leche y 25 ml de café expreso, en ocasiones se agrega cacao en polvo o canela según el gusto del consumidor.",
        "categoria": {
            "nombre": "Preparado",
            "id": "preparado"
        },
        "precio": 350,
        "cantidad": 1
    },

    {
        "id": "cafe-2",
        "titulo": "Australiano",
        "imagen": "./img/products/australiano.jpg",
        "detalles":"Se trata del café Specialty, que es el que ha sido debidamente tratado, desde sus orígenes (las plantaciones) hasta su elaboración en una cafetería, con una buena máquina y un barista correctamente formado.",
        "categoria": {
            "nombre": "Preparado",
            "id": "preparado"
        },
        "precio": 400,
        "cantidad": 1
    },

    {
        "id": "cafe-3",
        "titulo": "Vienés",
        "imagen": "./img/products/viena.jpg",
        "detalles":"Preparamos un expreso doble al gusto, más o menos fuerte, y lo azucaramos. Lo ponemos en el fondo de la taza y coronamos con la nata muy batida o montada. Espolvoreamos con canela o cacao en polvo y decoramos con un barquillo o una pasta ligera.",
        "categoria": {
            "nombre": "Preparado",
            "id": "preparado"
        },
        "precio": 420,
        "cantidad": 1
    },

    {
        "id": "cafe-4",
        "titulo": "Frappé",
        "imagen": "./img/products/helado.jpg",
        "detalles":"Se compone de café u otro ingrediente de base (por ejemplo, crema), mezclado con hielo y otros ingredientes diversos, coronado con crema batida.",
        "categoria": {
            "nombre": "Preparado",
            "id": "preparado"
        },
        "precio": 450,
        "cantidad": 1
    },

    {
        "id": "cafe-5",
        "titulo": "Macchiato",
        "imagen": "./img/products/macchiato.jpg",
        "detalles":" Café cortado típico de Italia que consiste en un expreso con una pequeña cantidad de leche caliente y espumada.",
        "categoria": {
            "nombre": "Preparado",
            "id": "preparado"
        },
        "precio": 480,
        "cantidad": 1
    },

    {
        "id": "cafe-6",
        "titulo": "Irish",
        "imagen": "./img/products/irish.jpg",
        "detalles": "Mezcla de whisky irlandés, una cucharada de azúcar y café, finalmente cubierto por dos centímetros de crema de leche o nata semimontada.",
        "categoria": {
            "nombre": "Preparado",
            "id": "preparado"
        },
        "precio": 460,
        "cantidad": 1
    },

    {
        "id": "cafe-7",
        "titulo": "Cardamomo",
        "imagen":"./img/products/cardamomo.png",
        "detalles":"Combina vodka lavado con grasa de pistacho con un trago de espresso y un jarabe de cardamomo casero. Tres vainas de cardamomo reemplazan la guarnición clásica de granos de café.",
        "categoria": {
            "nombre": "Preparado",
            "id": "preparado"
        },
        "precio": 550,
        "cantidad": 1
    },

    {
        "id": "cafe-8",
        "titulo": "Bolivia p/ filtro",
        "imagen":"./img/products/filtro-bolivia.jpg",
        "detalles":"Varietal: Caturra, Típica. Café tostado con buen cuerpo. Cosechado a 1413m de altura en la Región de Caranavi. Con notas frutales, pomelo dulce, y presencia de vainilla y cacao, de acidez media.",
        "categoria": {
            "nombre": "Envasado",
            "id": "envasado"
        },
        "precio": 3700,
        "cantidad": 1
    },

    {
        "id": "cafe-9",
        "titulo": "Colombia cápsulas",
        "imagen":"./img/products/capsulas-colombia.jpg",
        "detalles": "Varietal: Caturra, Típica, Castilla. El mejor Café de especialidad para recargar tus cápsulas Caffettino.",
        "categoria": {
            "nombre": "Envasado",
            "id": "envasado"
        },
        "precio": 3500,
        "cantidad": 1
    },

    {
        "id": "cafe-10",
        "titulo": "Nicaragua cápsulas",
        "imagen":"./img/products/nicaragua.jpg",
        "detalles":"Varietal: Javanica, Caturra. Café de intensidad media y muy aromático, fresco y alimonado. Con notas de cacao. Sutilmente floral, su aroma recuerda al limoncillo, jazmín y azhar.",
        "categoria": {
            "nombre": "Envasado",
            "id": "envasado"
        },
        "precio": 3700,
        "cantidad": 1
    },

    {
        "id": "cafe-11",
        "titulo": "Brasil molido",
        "imagen":"./img/products/brasil-molido.jpg",
        "detalles": "Varietal: Catuai rojo. La publicación corresponde a 250 Gr. de café molido en su punto justo que te permiten hacer 50 pocillos en sistemas Nespresso.",
        "categoria": {
            "nombre": "Envasado",
            "id": "envasado"
        },
        "precio": 3100,
        "cantidad": 1
    },

    {
        "id": "cafe-12",
        "titulo": "Colombia en granos",
        "imagen":"./img/products/colombia-granos.jpg",
        "detalles":"Varietal: Geisha. Café tostado con cuerpo ligero. Cosechado a 1900m de altura. Con acidez cítrica y notas frutales, notas florales como jazmín. Residual extendido.",
        "categoria": {
            "nombre": "Envasado",
            "id": "envasado"
        },
        "precio": 4900,
        "cantidad": 1
    },

    {
        "id": "cafe-13",
        "titulo": "Brasil intenso",
        "imagen":"./img/products/brasil-intenso.jpg",
        "detalles":"Varietal: Catuai rojo. Café intenso con marcadas notas de cacao, muy buen aroma y cuerpo.",
        "categoria": {
            "nombre": "Envasado",
            "id": "envasado"
        },
        "precio": 3900,
        "cantidad": 1
    },

    {
        "id": "cafe-14",
        "titulo": "Bolivia en granos",
        "imagen":"./img/products/bolivia-granos.jpg",
        "detalles":"Varietal: Catuai, Caturra, Typica. Café tostado con buen cuerpo. Cosechado a 1500m de altura. Con acidez y dulzor cítricos, pasas de uva, notas a chocolate con leche y vainilla.",
        "categoria": {
            "nombre": "Envasado",
            "id": "envasado"
        },
        "precio": 3600,
        "cantidad": 1
    },

    {
        "id": "cafe-15",
        "titulo": "Colombia premium",
        "imagen":"./img/products/colombia-premium.jpg",
        "detalles":"Varietal: Caturra, Típica, Castilla. Es un café intenso, con notas cítricas y muy buen cuerpo, directo de origen, en granos.",
        "categoria": {
            "nombre": "Envasado",
            "id": "envasado"
        },
        "precio": 9000,
        "cantidad": 1
    }
]